mcp_sqlite_manager/__init__.py
mcp_sqlite_manager/__main__.py
mcp_sqlite_manager/sqlite_tools.py
mcp_sqlite_manager-1.0.0.dist-info/METADATA
mcp_sqlite_manager-1.0.0.dist-info/WHEEL
mcp_sqlite_manager-1.0.0.dist-info/entry_points.txt
mcp_sqlite_manager-1.0.0.dist-info/RECORD
