Metadata-Version: 2.1
Name: mcp-sqlite-manager
Version: 1.0.0
Summary: An MCP server to interact with SQLite databases
Home-page: https://github.com/jonnyhoff/mcp-sqlite-manager
License: MIT
Author: Jonathan Hoffman
Author-email: jonathan.hoffman91@gmail.com
Requires-Python: >=3.11,<4.0
Classifier: License :: OSI Approved :: MIT License
Classifier: Programming Language :: Python :: 3
Classifier: Programming Language :: Python :: 3.11
Requires-Dist: fastmcp (>=2.1.1,<3.0.0)
Project-URL: Repository, https://github.com/jonnyhoff/mcp-sqlite-manager
